{
  "id": "bradley-wiggins",
  "first_name": "Bradley",
  "last_name": "Wiggins",
  "country": "Royaume-Uni",
  "years": {
    "2006": {
      "position": "123",
      "nb_wins": 0
    },
    "2007": {
      "position": "Abandon",
      "nb_wins": 0
    },
    "2008": {
      "position": "Non partant",
      "nb_wins": 0
    },
    "2009": {
      "position": "3",
      "nb_wins": 0
    },
    "2010": {
      "position": "24",
      "nb_wins": 0
    },
    "2011": {
      "position": "Abandon",
      "nb_wins": 0
    },
    "2012": {
      "position": "1",
      "nb_wins": 2
    }
  },
  "wins": [
    2012
  ],
  "wins_age": [
    32
  ],
  "birthdate": "28/04/1980",
  "birthyear": 1980,
  "deathdate": null,
  "bio": "Le premier coureur britannique à remporter le Tour.",
  "period": {
    "min": 2006,
    "max": 2012
  }
}